tuniv_zemcad/__init__.py
tuniv_zemcad-0.1.dist-info/DESCRIPTION.rst
tuniv_zemcad-0.1.dist-info/METADATA
tuniv_zemcad-0.1.dist-info/RECORD
tuniv_zemcad-0.1.dist-info/WHEEL
tuniv_zemcad-0.1.dist-info/metadata.json
tuniv_zemcad-0.1.dist-info/top_level.txt
