Metadata-Version: 2.0
Name: tuniv-zemcad
Version: 0.1
Summary: tuniv zemcad library
Home-page: https://github.com/tlubenov/zemcad2gis
Author: Todor Lubenov
Author-email: tlubenov@gmail.com
License: MIT
Platform: UNKNOWN
